[
  {
    "id": "10",
    "name": "Rain",
    "avatar": "/fighters/Rain.jpg",
    "gif": "/gifs/Rain_show.gif",
    "vs": "/fighters/Rain_vs.png"
  },
  {
    "id": "11",
    "name": "Reptile",
    "avatar": "/fighters/Reptile.jpg",
    "gif": "/gifs/Reptile_show.gif",
    "vs": "/fighters/Reptile_vs.png"
  },
  {
    "id": "12",
    "name": "Stryker",
    "avatar": "/fighters/Stryker.jpg",
    "gif": "/gifs/Stryker_show.gif",
    "vs": "/fighters/Stryker_vs.png"
  },
  {
    "id": "13",
    "name": "Jax",
    "avatar": "/fighters/Jax.jpg",
    "gif": "/gifs/Jax_show.gif",
    "vs": "/fighters/Jax_vs.png"
  },
  {
    "id": "14",
    "name": "Nightwolf",
    "avatar": "/fighters/Nightwolf.jpg",
    "gif": "/gifs/Nightwolf_show.gif",
    "vs": "/fighters/Nightwolf_vs.png"
  },
  {
    "id": "15",
    "name": "Jade",
    "avatar": "/fighters/Jade.jpg",
    "gif": "/gifs/Jade_show.gif",
    "vs": "/fighters/Jade_vs.png"
  },
  {
    "id": "16",
    "name": "Bi-Han",
    "avatar": "/fighters/Bi-Han.jpg",
    "gif": "/gifs/Bi-Han_show.gif",
    "vs": "/fighters/Bi-Han_vs.png"
  },
  {
    "id": "20",
    "name": "Sonya",
    "avatar": "/fighters/Sonya.jpg",
    "gif": "/gifs/Sonya_show.gif",
    "vs": "/fighters/Sonya_vs.png"
  },
  {
    "id": "21",
    "name": "Kano",
    "avatar": "/fighters/Kano.jpg",
    "gif": "/gifs/Kano_show.gif",
    "vs": "/fighters/Kano_vs.png"
  },
  {
    "id": "22",
    "name": "Mileena",
    "avatar": "/fighters/Mileena.jpg",
    "gif": "/gifs/Mileena_show.gif",
    "vs": "/fighters/Mileena_vs.png"
  },
  {
    "id": "23",
    "name": "center",
    "avatar": "/fighters/center.jpg"
  },
  {
    "id": "24",
    "name": "Kuai-Liang",
    "avatar": "/fighters/Kuai-Liang.jpg",
    "gif": "/gifs/Kuai-Liang_show.gif",
    "vs": "/fighters/Kuai-Liang_vs.png"
  },
  {
    "id": "25",
    "name": "Subzero",
    "avatar": "/fighters/Subzero.jpg",
    "gif": "/gifs/Subzero_show.gif",
    "vs": "/fighters/Subzero_vs.png"
  },
  {
    "id": "26",
    "name": "Kung-Lao",
    "avatar": "/fighters/Kung-Lao.jpg",
    "gif": "/gifs/Kung-Lao_show.gif",
    "vs": "/fighters/Kung-Lao_vs.png"
  },
  {
    "id": "31",
    "name": "Sector",
    "avatar": "/fighters/Sector.jpg",
    "gif": "/gifs/Sector_show.gif",
    "vs": "/fighters/Sector_vs.png"
  },
  {
    "id": "32",
    "name": "Kitana",
    "avatar": "/fighters/Kitana.jpg",
    "gif": "/gifs/Kitana_show.gif",
    "vs": "/fighters/Kitana_vs.png"
  },
  {
    "id": "33",
    "name": "Ermac",
    "avatar": "/fighters/Ermac.jpg",
    "gif": "/gifs/Ermac_show.gif",
    "vs": "/fighters/Ermac_vs.png"
  },
  {
    "id": "34",
    "name": "Scorpion",
    "avatar": "/fighters/Scorpion.jpg",
    "gif": "/gifs/Scorpion_show.gif",
    "vs": "/fighters/Scorpion_vs.png"
  },
  {
    "id": "35",
    "name": "Cyrax",
    "avatar": "/fighters/Cyrax.jpg",
    "gif": "/gifs/Cyrax_show.gif",
    "vs": "/fighters/Cyrax_vs.png"
  },
  {
    "id": "41",
    "name": "Kabal",
    "avatar": "/fighters/Kabal.jpg",
    "gif": "/gifs/Kabal_show.gif",
    "vs": "/fighters/Kabal_vs.png"
  },
  {
    "id": "42",
    "name": "Sindel",
    "avatar": "/fighters/Sindel.jpg",
    "gif": "/gifs/Sindel_show.gif",
    "vs": "/fighters/Sindel_vs.png"
  },
  {
    "id": "43",
    "name": "Smoke",
    "avatar": "/fighters/Smoke.jpg",
    "gif": "/gifs/Smoke_show.gif",
    "vs": "/fighters/Smoke_vs.png"
  },
  {
    "id": "44",
    "name": "Liu-Kang",
    "avatar": "/fighters/Liu-Kang.jpg",
    "gif": "/gifs/Liu-Kang_show.gif",
    "vs": "/fighters/Liu-Kang_vs.png"
  },
  {
    "id": "45",
    "name": "Shang-Tsung",
    "avatar": "/fighters/Shang-Tsung.jpg",
    "gif": "/gifs/Shang-Tsung_show.gif",
    "vs": "/fighters/Shang-Tsung_vs.png"
  }
]
